nirfmxspecan/__init__.py
nirfmxspecan/acp.py
nirfmxspecan/acp_configuration.py
nirfmxspecan/acp_results.py
nirfmxspecan/ampm.py
nirfmxspecan/ampm_configuration.py
nirfmxspecan/ampm_results.py
nirfmxspecan/attributes.py
nirfmxspecan/ccdf.py
nirfmxspecan/ccdf_configuration.py
nirfmxspecan/ccdf_results.py
nirfmxspecan/chp.py
nirfmxspecan/chp_configuration.py
nirfmxspecan/chp_results.py
nirfmxspecan/dpd.py
nirfmxspecan/dpd_apply_dpd.py
nirfmxspecan/dpd_configuration.py
nirfmxspecan/dpd_pre_dpd.py
nirfmxspecan/dpd_results.py
nirfmxspecan/enums.py
nirfmxspecan/errors.py
nirfmxspecan/examples/nirfmxspecan_acp.py
nirfmxspecan/examples/nirfmxspecan_chp.py
nirfmxspecan/examples/nirfmxspecan_spectrum.py
nirfmxspecan/examples/nirfmxspecan_txp_grpc.py
nirfmxspecan/fcnt.py
nirfmxspecan/fcnt_configuration.py
nirfmxspecan/fcnt_results.py
nirfmxspecan/grpc_session_options.py
nirfmxspecan/harm.py
nirfmxspecan/harm_configuration.py
nirfmxspecan/harm_results.py
nirfmxspecan/idpd.py
nirfmxspecan/idpd_configuration.py
nirfmxspecan/idpd_results.py
nirfmxspecan/im.py
nirfmxspecan/im_configuration.py
nirfmxspecan/im_results.py
nirfmxspecan/internal/_custom_types.py
nirfmxspecan/internal/_grpc_stub_interpreter.py
nirfmxspecan/internal/_helper.py
nirfmxspecan/internal/_library.py
nirfmxspecan/internal/_library_interpreter.py
nirfmxspecan/internal/_library_singleton.py
nirfmxspecan/internal/nidevice_pb2.py
nirfmxspecan/internal/nidevice_pb2_grpc.py
nirfmxspecan/internal/nirfmxspecan_pb2.py
nirfmxspecan/internal/nirfmxspecan_pb2_grpc.py
nirfmxspecan/internal/nirfmxspecan_restricted_pb2.py
nirfmxspecan/internal/nirfmxspecan_restricted_pb2_grpc.py
nirfmxspecan/internal/session_pb2.py
nirfmxspecan/internal/session_pb2_grpc.py
nirfmxspecan/iq.py
nirfmxspecan/iq_configuration.py
nirfmxspecan/iq_results.py
nirfmxspecan/marker.py
nirfmxspecan/marker_configuration.py
nirfmxspecan/marker_results.py
nirfmxspecan/nf.py
nirfmxspecan/nf_configuration.py
nirfmxspecan/nf_results.py
nirfmxspecan/obw.py
nirfmxspecan-26.0.0.dist-info/licenses/LICENSE
nirfmxspecan-26.0.0.dist-info/METADATA
nirfmxspecan-26.0.0.dist-info/WHEEL
nirfmxspecan-26.0.0.dist-info/RECORD
